csulb_mock_dataset/__init__.py
csulb_mock_dataset/cmp1.csv
csulb_mock_dataset/data.py
csulb_mock_student_dataset/__init__.py
csulb_mock_student_dataset/cmp1.csv
csulb_mock_student_dataset/data.py
files/__init__.py
files/data.py
HE_Dataset-0.2.1.dist-info/METADATA
HE_Dataset-0.2.1.dist-info/WHEEL
HE_Dataset-0.2.1.dist-info/top_level.txt
HE_Dataset-0.2.1.dist-info/RECORD
