Metadata-Version: 2.1
Name: HE-Dataset
Version: 0.2.1
Summary: A simple package containing a CSV dataset
Author: Gurucharan Raju
Author-email: Gurucharan.Raju-SA@csulb.edu@csulb.edu
License: MIT
Requires-Dist: pandas
